Workbook

Sheet CONTROL
A1: ПАНЕЛЬ УПРАВЛЕНИЯ - ВВОДНЫЕ ДАННЫЕ
A3: Параметр | B3: Значение | C3: Единица | D3: Комментарий
A4: ПОЛЬЗОВАТЕЛИ
A5: Пользователи (месяц 1) | B5: 5000 | C5: чел | D5: MVP старт
A6: Рост пользователей | B6: 15 | C6: % | D6: Ежемесячный прирост
A7: Текущий месяц расчета | B7: 1 | C7: мес | D7: Меняй для прогноза (1-12)
A9: ИСПОЛЬЗОВАНИЕ НА ПОЛЬЗОВАТЕЛЯ
A10: Примерок на пользователя | B10: 3 | C10: шт | D10: Pixelcut Try-On
A11: Анимаций (видео) на пользователя | B11: 1 | C11: шт | D11: Video generation
A12: LLM запросов на пользователя | B12: 5 | C12: шт | D12: Чат/рекомендации
A14: РАЗМЕРЫ ФАЙЛОВ
A15: Средний размер фото | B15: 3 | C15: MB | D15: Входное изображение
A16: Средний размер видео | B16: 15 | C16: MB | D16: Сгенерированное видео
A18: МАСШТАБИРОВАНИЕ
A19: Пользователей на 1 сервер | B19: 10000 | C19: чел | D19: Порог для автоскейла
A21: РАСЧЕТНЫЕ ЗНАЧЕНИЯ
A22: Пользователи (текущий месяц) | B22: =IF(B7=1,B5,ROUND(B5*(1+B6/100)^(B7-1),0)) | C22: чел | D22: С учетом роста
A23: Всего примерок | B23: =B22*B10 | C23: шт | D23: В месяц
A24: Всего видео | B24: =B22*B11 | C24: шт | D24: В месяц
A25: Всего LLM запросов | B25: =B22*B12 | C25: шт | D25: В месяц
A26: Хранилище фото (GB) | B26: =B23*B15/1024 | C26: GB | D26: В месяц
A27: Хранилище видео (GB) | B27: =B24*B16/1024 | C27: GB | D27: В месяц
A28: Требуется серверов | B28: =CEILING(B22/B19,1) | C28: шт | D28: Автоскейл

Sheet AI_Generation
A1: ИИ И ГЕНЕРАЦИЯ - ЗАТРАТЫ
A3: Сервис / Операция | B3: Цена за 1 опер. ($) | C3: Количество | D3: Итого ($) | E3: Комментарий
A4: ВИРТУАЛЬНЫЕ ПРИМЕРКИ
A5: Pixelcut Try-On API | B5: 0.1 | C5: =CONTROL!B23 | D5: =B5*C5 | E5: 10 кредитов = $0.10/изображение
A7: ВИДЕО ГЕНЕРАЦИЯ
A8: Video Animation (MiniMax/Runway) | B8: 0.5 | C8: =CONTROL!B24 | D8: =B9*C9 | E8: ~$0.50 за 5 сек видео
A10: LLM / ТЕКСТ
A11: OpenAI GPT-4o (1K токенов) | B11: 0.005 | C11: =CONTROL!B25*2 | D11: =B13*C13 | E11: input+output ~2K токенов/запрос
A12: OpenAI GPT-4o-mini (backup) | B12: 0.0003 | C12: =CONTROL!B25*0.5 | D12: =B14*C14 | E12: Легкие запросы
A13: Embeddings (поиск) | B13: 0.0001 | C13: =CONTROL!B25 | D13: =B15*C15 | E13: Рекомендации
A15: ДОПОЛНИТЕЛЬНЫЕ AI
A16: Background Removal | B16: 0.02 | C16: =CONTROL!B23*0.5 | D16: =B19*C19 | E16: 50% примерок
A17: Image Upscale | B17: 0.01 | C17: =CONTROL!B23*0.3 | D17: =B20*C20 | E17: 30% примерок
A22: ИТОГО AI И ГЕНЕРАЦИЯ | D22: =SUM(D5:D21)

Sheet Infrastructure
A1: ИНФРАСТРУКТУРА - СЕРВЕРЫ И СЕРВИСЫ
A3: Ресурс | B3: Цена/мес ($) | C3: Количество | D3: Итого ($) | E3: Провайдер / Комментарий
A4: СЕРВЕРЫ
A5: Backend VPS (4 CPU / 8 GB) | B5: 45 | C5: =CONTROL!B28 | D5: =B5*C5 | E5: DigitalOcean / Vultr
A6: Worker Server (AI Queue) | B6: 60 | C6: =CEILING(CONTROL!B28/2,1) | D6: =B6*C6 | E6: Для обработки задач
A8: БАЗЫ ДАННЫХ
A9: PostgreSQL Managed | B9: 25 | C9: 1 | D9: =B10*C10 | E9: DigitalOcean / Supabase
A10: Redis (кэш/очереди) | B10: 15 | C10: 1 | D10: =B11*C11 | E10: Upstash / Redis Cloud
A12: ХРАНИЛИЩЕ
A13: Object Storage (за GB) | B13: 0.02 | C13: =CONTROL!B26+CONTROL!B27 | D13: =B15*C15 | E13: S3 / Cloudflare R2
A14: CDN Bandwidth (за GB) | B14: 0.01 | C14: =(CONTROL!B26+CONTROL!B27)*3 | D14: =B16*C16 | E14: x3 от хранилища
A16: ДОПОЛНИТЕЛЬНО
A17: SSL / Domain | B17: 0 | C17: 1 | D17: =B20*C20 | E17: Let's Encrypt бесплатно
A18: Monitoring (Sentry) | B18: 26 | C18: 1 | D18: =B21*C21 | E18: Team plan
A19: CI/CD (GitHub Actions) | B19: 0 | C19: 1 | D19: =B22*C22 | E19: Free tier достаточно
A20: Email Service (Resend) | B20: 20 | C20: 1 | D20: =B23*C23 | E20: 10K emails/month
A25: ИТОГО ИНФРАСТРУКТУРА | D25: =SUM(D5:D24)

Sheet Traffic
A1: ТРАФИК И КОММУНИКАЦИИ
A3: Канал | B3: Цена за событие ($) | C3: Количество | D3: Итого ($) | E3: Комментарий
A4: УВЕДОМЛЕНИЯ
A5: Push Notifications | B5: 0.0001 | C5: =CONTROL!B22*10 | D5: =B5*C5 | E5: ~10 пушей/пользователь
A6: Email (транзакционные) | B6: 0.001 | C6: =CONTROL!B22*3 | D6: =B6*C6 | E6: ~3 email/пользователь
A7: SMS (критичные) | B7: 0.05 | C7: =CONTROL!B22*0.1 | D7: =B7*C7 | E7: 10% пользователей
A9: API И ИНТЕГРАЦИИ
A10: Webhook calls | B10: 0.0001 | C10: =CONTROL!B22*5 | D10: =B11*C11 | E10: ~5 webhooks/пользователь
A11: Payment Gateway (Stripe) | B11: 0 | C11: 1 | D11: =B12*C12 | E11: % от транзакций отдельно
A12: Analytics (Mixpanel) | B12: 0 | C12: 1 | D12: =B13*C13 | E12: Free tier
A15: ИТОГО ТРАФИК | D15: =SUM(D5:D14)

Sheet TOTAL
A1: СВОДКА РАСХОДОВ
A3: Расчет для месяца: | B3: =CONTROL!B7 | C3: Пользователей: | D3: =CONTROL!B22
A5: Категория | B5: Сумма ($) | C5: % от общего | D5: Комментарий
A6: AI и Генерация | B6: =AI_Generation!D22 | C6: =B6/$B$10*100 | D6: Pixelcut, Video, LLM
A7: Инфраструктура | B7: =Infrastructure!D25 | C7: =B7/$B$10*100 | D7: Серверы, БД, Хранилище
A8: Трафик и Коммуникации | B8: =Traffic!D15 | C8: =B8/$B$10*100 | D8: Push, Email, SMS
A10: ОБЩИЙ ИТОГ | B10: =SUM(B6:B8) | C10: 100%
A12: UNIT ECONOMICS
A13: Стоимость 1 пользователя | B13: =B10/CONTROL!B22 | C13: $ | D13: Средняя за месяц
A14: Стоимость 1 примерки | B14: =AI_Generation!D5/CONTROL!B23 | C14: $ | D14: Только Pixelcut
A15: Стоимость 1 видео | B15: =AI_Generation!D9/CONTROL!B24 | C15: $ | D15: Только генерация
A16: Себестоимость образа (полная) | B16: =(AI_Generation!D5+AI_Generation!D19+AI_Generation!D20)/CONTROL!B23 | C16: $ | D16: Try-on + обработка

Sheet Forecast_6M
A1: ПРОГНОЗ НА 6 МЕСЯЦЕВ
A3: Показатель | B3: Месяц 1 | C3: Месяц 2 | D3: Месяц 3 | E3: Месяц 4 | F3: Месяц 5 | G3: Месяц 6 | H3: Рост
A4: Пользователи | B4: =CONTROL!B5 | C4: =B4*(1+CONTROL!$B$6/100) | D4: =C4*(1+CONTROL!$B$6/100) | E4: =D4*(1+CONTROL!$B$6/100) | F4: =E4*(1+CONTROL!$B$6/100) | G4: =F4*(1+CONTROL!$B$6/100) | H4: =G4/B4-1
A5: Примерок (всего) | B5: =B4*CONTROL!$B$10 | C5: =C4*CONTROL!$B$10 | D5: =D4*CONTROL!$B$10 | E5: =E4*CONTROL!$B$10 | F5: =F4*CONTROL!$B$10 | G5: =G4*CONTROL!$B$10 | H5: =G5/B5-1
A7: ЗАТРАТЫ ($)
A8: AI и Генерация | B8: =B5*0.1 + B4*CONTROL!$B$11*0.5 + B4*CONTROL!$B$12*0.005*2 | C8: =C5*0.1 + C4*CONTROL!$B$11*0.5 + C4*CONTROL!$B$12*0.005*2 | D8: =D5*0.1 + D4*CONTROL!$B$11*0.5 + D4*CONTROL!$B$12*0.005*2 | E8: =E5*0.1 + E4*CONTROL!$B$11*0.5 + E4*CONTROL!$B$12*0.005*2 | F8: =F5*0.1 + F4*CONTROL!$B$11*0.5 + F4*CONTROL!$B$12*0.005*2 | G8: =G5*0.1 + G4*CONTROL!$B$11*0.5 + G4*CONTROL!$B$12*0.005*2 | H8: =G8/B8-1
A9: Инфраструктура | B9: =45*CEILING(B4/CONTROL!$B$19,1)+60*CEILING(CEILING(B4/CONTROL!$B$19,1)/2,1)+40+15+26+20 | C9: =45*CEILING(C4/CONTROL!$B$19,1)+60*CEILING(CEILING(C4/CONTROL!$B$19,1)/2,1)+40+15+26+20 | D9: =45*CEILING(D4/CONTROL!$B$19,1)+60*CEILING(CEILING(D4/CONTROL!$B$19,1)/2,1)+40+15+26+20 | E9: =45*CEILING(E4/CONTROL!$B$19,1)+60*CEILING(CEILING(E4/CONTROL!$B$19,1)/2,1)+40+15+26+20 | F9: =45*CEILING(F4/CONTROL!$B$19,1)+60*CEILING(CEILING(F4/CONTROL!$B$19,1)/2,1)+40+15+26+20 | G9: =45*CEILING(G4/CONTROL!$B$19,1)+60*CEILING(CEILING(G4/CONTROL!$B$19,1)/2,1)+40+15+26+20 | H9: =G9/B9-1
A10: Трафик | B10: =B4*10*0.0001+B4*3*0.001+B4*0.1*0.05 | C10: =C4*10*0.0001+C4*3*0.001+C4*0.1*0.05 | D10: =D4*10*0.0001+D4*3*0.001+D4*0.1*0.05 | E10: =E4*10*0.0001+E4*3*0.001+E4*0.1*0.05 | F10: =F4*10*0.0001+F4*3*0.001+F4*0.1*0.05 | G10: =G4*10*0.0001+G4*3*0.001+G4*0.1*0.05 | H10: =G10/B10-1
A12: ИТОГО МЕСЯЦ | B12: =B8+B9+B10 | C12: =C8+C9+C10 | D12: =D8+D9+D10 | E12: =E8+E9+E10 | F12: =F8+F9+F10 | G12: =G8+G9+G10 | H12: =G12/B12-1
A13: Накопительно | B13: =B12 | C13: =B13+C12 | D13: =C13+D12 | E13: =D13+E12 | F13: =E13+F12 | G13: =F13+G12
A15: UNIT ECONOMICS
A16: $/пользователь | B16: =B12/B4 | C16: =C12/C4 | D16: =D12/D4 | E16: =E12/E4 | F16: =F12/F4 | G16: =G12/G4 | H16: =G16/B16-1
A17: $/примерка | B17: =B8/B5 | C17: =C8/C5 | D17: =D8/D5 | E17: =E8/E5 | F17: =F8/F5 | G17: =G8/G5 | H17: =G17/B17-1

Sheet Token_Calculator
A1: КАЛЬКУЛЯТОР СТОИМОСТИ ТОКЕНОВ
A3: Провайдер / Модель | B3: Input ($/1M) | C3: Output ($/1M) | D3: Токенов/запрос | E3: Запросов | F3: Итого ($)
A4: OPENAI
A5: GPT-4o | B5: 2.5 | C5: 10 | D5: 2000 | E5: =CONTROL!B25 | F5: =(B5*C5/1000000+C5*D5/1000000)*E5
A6: GPT-4o-mini | B6: 0.15 | C6: 0.6 | D6: 1500 | E6: =CONTROL!B25*0.5 | F6: =(B6*D6/1000000+C6*D6/1000000)*E6
A7: GPT-4-turbo | B7: 10 | C7: 30 | D7: 2000 | E7: 0 | F7: =(B7*D7/1000000+C7*D7/1000000)*E7
A9: ANTHROPIC
A10: Claude 3.5 Sonnet | B10: 3 | C10: 15 | D10: 2000 | E10: 0 | F10: =(B11*D11/1000000+C11*D11/1000000)*E11
A11: Claude 3 Haiku | B11: 0.25 | C11: 1.25 | D11: 1500 | E11: 0 | F11: =(B12*D12/1000000+C12*D12/1000000)*E12
A13: GOOGLE
A14: Gemini 1.5 Pro | B14: 1.25 | C14: 5 | D14: 2000 | E14: 0 | F14: =(B16*D16/1000000+C16*D16/1000000)*E16
A15: Gemini 1.5 Flash | B15: 0.075 | C15: 0.3 | D15: 1500 | E15: 0 | F15: =(B17*D17/1000000+C17*D17/1000000)*E17
A17: EMBEDDINGS
A18: text-embedding-3-small | B18: 0.02 | C18: 0 | D18: 500 | E18: =CONTROL!B25 | F18: =B21*D21/1000000*E21
A19: text-embedding-3-large | B19: 0.13 | C19: 0 | D19: 500 | E19: 0 | F19: =B22*D22/1000000*E22
A24: ИТОГО LLM ЗАТРАТЫ | F24: =SUM(F5:F23)
A26: ПАМЯТКА: 1M = 1,000,000 токенов. ~750 слов = ~1000 токенов
